[
    {
        "sub_start": 0.0,
        "sub_end": 435.0,
        "bestObjV": 3748.4085309776538,
        "bestParams": [
            2955.0,
            32.49581328716503,
            0.9
        ]
    },
    {
        "sub_start": 21.75,
        "sub_end": 435.0,
        "bestObjV": 3671.953713773197,
        "bestParams": [
            2955.0,
            31.14763848670387,
            0.9
        ]
    },
    {
        "sub_start": 43.5,
        "sub_end": 435.0,
        "bestObjV": 3223.4038410894186,
        "bestParams": [
            2955.0,
            22.117212775818007,
            0.9
        ]
    },
    {
        "sub_start": 65.25,
        "sub_end": 435.0,
        "bestObjV": 2472.8631021626315,
        "bestParams": [
            2955.0,
            0.30357191109209536,
            0.9
        ]
    },
    {
        "sub_start": 87.0,
        "sub_end": 435.0,
        "bestObjV": 2333.550148516284,
        "bestParams": [
            2955.0,
            0.358217716838945,
            0.9
        ]
    },
    {
        "sub_start": 108.75,
        "sub_end": 435.0,
        "bestObjV": 1774.6321762948735,
        "bestParams": [
            438.20567717602955,
            2.2435684427942393,
            0.2584430275821929
        ]
    },
    {
        "sub_start": 130.5,
        "sub_end": 435.0,
        "bestObjV": 1680.4007969537915,
        "bestParams": [
            440.1076439275221,
            2.1940540852365187,
            0.6299012098369677
        ]
    },
    {
        "sub_start": 152.25,
        "sub_end": 435.0,
        "bestObjV": 1629.0064272868865,
        "bestParams": [
            440.16345333623224,
            2.1322712167468403,
            0.5306287839240993
        ]
    },
    {
        "sub_start": 174.0,
        "sub_end": 435.0,
        "bestObjV": 1400.5424241546837,
        "bestParams": [
            446.75938344487724,
            2.983989363256769,
            0.39064847160803634
        ]
    },
    {
        "sub_start": 195.75,
        "sub_end": 435.0,
        "bestObjV": 993.2927706216309,
        "bestParams": [
            463.3577208061815,
            4.498039044889392,
            0.2867309505189152
        ]
    },
    {
        "sub_start": 217.5,
        "sub_end": 435.0,
        "bestObjV": 849.4914661890448,
        "bestParams": [
            440.0317270369136,
            2.4561641746349023,
            0.20496282487054956
        ]
    },
    {
        "sub_start": 239.25,
        "sub_end": 435.0,
        "bestObjV": 842.0340031457308,
        "bestParams": [
            443.2825751200037,
            2.542917654926166,
            0.13733865736371456
        ]
    },
    {
        "sub_start": 261.0,
        "sub_end": 435.0,
        "bestObjV": 760.8470821121495,
        "bestParams": [
            514.5326949345479,
            9.556974663320036,
            0.27239540312937854
        ]
    },
    {
        "sub_start": 282.75,
        "sub_end": 435.0,
        "bestObjV": 491.9209703659581,
        "bestParams": [
            620.1675583842169,
            19.04361209715732,
            0.2755666286907666
        ]
    },
    {
        "sub_start": 304.5,
        "sub_end": 435.0,
        "bestObjV": 459.13995286479854,
        "bestParams": [
            615.6913490934916,
            19.284003315415166,
            0.5498453747452915
        ]
    },
    {
        "sub_start": 0.0,
        "sub_end": 430.0,
        "bestObjV": 3739.8375470900996,
        "bestParams": [
            2950.0,
            32.795174166061734,
            0.9
        ]
    },
    {
        "sub_start": 21.75,
        "sub_end": 430.0,
        "bestObjV": 3665.079775661807,
        "bestParams": [
            2950.0,
            31.38180107316094,
            0.9
        ]
    },
    {
        "sub_start": 43.5,
        "sub_end": 430.0,
        "bestObjV": 3219.75763569389,
        "bestParams": [
            2950.0,
            22.10443723995553,
            0.9
        ]
    },
    {
        "sub_start": 65.25,
        "sub_end": 430.0,
        "bestObjV": 2469.221572096748,
        "bestParams": [
            2950.0,
            0.37558973188795686,
            0.9
        ]
    },
    {
        "sub_start": 87.0,
        "sub_end": 430.0,
        "bestObjV": 2329.100942880049,
        "bestParams": [
            2950.0,
            0.2851496233169871,
            0.9
        ]
    },
    {
        "sub_start": 108.75,
        "sub_end": 430.0,
        "bestObjV": 1630.057663353879,
        "bestParams": [
            430.21246134724197,
            1.7712920023101448,
            0.6382138150200612
        ]
    },
    {
        "sub_start": 130.5,
        "sub_end": 430.0,
        "bestObjV": 1594.9336996276993,
        "bestParams": [
            438.5990795983758,
            1.710970637545136,
            0.40142113782105054
        ]
    },
    {
        "sub_start": 152.25,
        "sub_end": 430.0,
        "bestObjV": 1573.1192135250237,
        "bestParams": [
            432.85242651414893,
            1.849566394252627,
            0.781208470167286
        ]
    },
    {
        "sub_start": 174.0,
        "sub_end": 430.0,
        "bestObjV": 1378.525656590469,
        "bestParams": [
            442.319793086356,
            2.7180617748391023,
            0.1560555987146785
        ]
    },
    {
        "sub_start": 195.75,
        "sub_end": 430.0,
        "bestObjV": 970.558034932901,
        "bestParams": [
            451.5447787821392,
            3.8578750025456507,
            0.6772385724421631
        ]
    },
    {
        "sub_start": 217.5,
        "sub_end": 430.0,
        "bestObjV": 851.1348555588664,
        "bestParams": [
            431.4384296982457,
            1.9146635299685055,
            0.6313448816599815
        ]
    },
    {
        "sub_start": 239.25,
        "sub_end": 430.0,
        "bestObjV": 770.7327032326373,
        "bestParams": [
            432.3770274271362,
            2.087873120505154,
            0.3506286464929292
        ]
    },
    {
        "sub_start": 261.0,
        "sub_end": 430.0,
        "bestObjV": 753.7360336030339,
        "bestParams": [
            536.7090514544834,
            11.294327945431714,
            0.1259019070387165
        ]
    },
    {
        "sub_start": 282.75,
        "sub_end": 430.0,
        "bestObjV": 474.4722470938014,
        "bestParams": [
            702.3361997629032,
            24.880304727384114,
            0.11656411381617797
        ]
    },
    {
        "sub_start": 304.5,
        "sub_end": 430.0,
        "bestObjV": 436.29605622164024,
        "bestParams": [
            890.2643266448376,
            40.0,
            0.5214556421279334
        ]
    },
    {
        "sub_start": 0.0,
        "sub_end": 425.0,
        "bestObjV": 3712.0131142478094,
        "bestParams": [
            2945.0,
            31.871033201549924,
            0.9
        ]
    },
    {
        "sub_start": 21.75,
        "sub_end": 425.0,
        "bestObjV": 3632.815190588083,
        "bestParams": [
            2945.0,
            30.20129628258295,
            0.9
        ]
    },
    {
        "sub_start": 43.5,
        "sub_end": 425.0,
        "bestObjV": 3164.9190342562933,
        "bestParams": [
            2945.0,
            19.233403462847225,
            0.9
        ]
    },
    {
        "sub_start": 65.25,
        "sub_end": 425.0,
        "bestObjV": 2416.8721976477004,
        "bestParams": [
            2945.0,
            0.3338505630529337,
            0.8999558560741724
        ]
    },
    {
        "sub_start": 87.0,
        "sub_end": 425.0,
        "bestObjV": 2266.5341754523793,
        "bestParams": [
            2945.0,
            0.23351448799285635,
            0.9
        ]
    },
    {
        "sub_start": 108.75,
        "sub_end": 425.0,
        "bestObjV": 4381.682407280391,
        "bestParams": [
            432.9447819131068,
            12.741160123261785,
            0.12865937541143888
        ]
    },
    {
        "sub_start": 130.5,
        "sub_end": 425.0,
        "bestObjV": 1527.3934478381052,
        "bestParams": [
            434.6602896611712,
            1.7991875296660167,
            0.2617857487777803
        ]
    },
    {
        "sub_start": 152.25,
        "sub_end": 425.0,
        "bestObjV": 1480.7861252167029,
        "bestParams": [
            433.25637879419395,
            2.0289746650704132,
            0.1979788225133927
        ]
    },
    {
        "sub_start": 174.0,
        "sub_end": 425.0,
        "bestObjV": 2341.3934503775886,
        "bestParams": [
            439.4709236654665,
            37.462175966242214,
            0.1
        ]
    },
    {
        "sub_start": 195.75,
        "sub_end": 425.0,
        "bestObjV": 971.890495320907,
        "bestParams": [
            446.5155284767451,
            3.255751915379538,
            0.7631130428582208
        ]
    },
    {
        "sub_start": 217.5,
        "sub_end": 425.0,
        "bestObjV": 834.7168486650576,
        "bestParams": [
            429.2041178907452,
            1.8547513201446622,
            0.6221172361769194
        ]
    },
    {
        "sub_start": 239.25,
        "sub_end": 425.0,
        "bestObjV": 743.2156090724169,
        "bestParams": [
            425.28943217902656,
            1.9097913994132774,
            0.3825294124591313
        ]
    },
    {
        "sub_start": 261.0,
        "sub_end": 425.0,
        "bestObjV": 731.9084236952095,
        "bestParams": [
            496.871907740076,
            8.725331852257618,
            0.15756717733468217
        ]
    },
    {
        "sub_start": 282.75,
        "sub_end": 425.0,
        "bestObjV": 475.6722783312021,
        "bestParams": [
            676.8222914778345,
            22.673497663532924,
            0.6390304555802963
        ]
    },
    {
        "sub_start": 304.5,
        "sub_end": 425.0,
        "bestObjV": 431.50450673702665,
        "bestParams": [
            897.1185846545832,
            40.0,
            0.6811874980277998
        ]
    },
    {
        "sub_start": 0.0,
        "sub_end": 420.0,
        "bestObjV": 3679.4574665958075,
        "bestParams": [
            2940.0,
            30.75827447955916,
            0.9
        ]
    },
    {
        "sub_start": 21.75,
        "sub_end": 420.0,
        "bestObjV": 3595.038613493345,
        "bestParams": [
            2940.0,
            28.780714617158704,
            0.9
        ]
    },
    {
        "sub_start": 43.5,
        "sub_end": 420.0,
        "bestObjV": 3101.742625656452,
        "bestParams": [
            2940.0,
            15.214856294599947,
            0.9
        ]
    },
    {
        "sub_start": 65.25,
        "sub_end": 420.0,
        "bestObjV": 2366.9531641865415,
        "bestParams": [
            2940.0,
            0.18479677501583291,
            0.9
        ]
    },
    {
        "sub_start": 87.0,
        "sub_end": 420.0,
        "bestObjV": 2205.477689758316,
        "bestParams": [
            2940.0,
            0.42403436895002256,
            0.9
        ]
    },
    {
        "sub_start": 108.75,
        "sub_end": 420.0,
        "bestObjV": 1460.280469153266,
        "bestParams": [
            425.9225560366117,
            0.2456438403605714,
            0.40659238625690514
        ]
    },
    {
        "sub_start": 130.5,
        "sub_end": 420.0,
        "bestObjV": 1390.377318593273,
        "bestParams": [
            429.5569443529571,
            0.9965697653918735,
            0.1
        ]
    },
    {
        "sub_start": 152.25,
        "sub_end": 420.0,
        "bestObjV": 1345.2204296358348,
        "bestParams": [
            421.26796516082675,
            1.360503083877699,
            0.1
        ]
    },
    {
        "sub_start": 174.0,
        "sub_end": 420.0,
        "bestObjV": 1214.8655511770953,
        "bestParams": [
            427.4937629853577,
            1.1687328263760497,
            0.11012093768209578
        ]
    },
    {
        "sub_start": 195.75,
        "sub_end": 420.0,
        "bestObjV": 916.2097176283553,
        "bestParams": [
            425.7505408084716,
            0.14165341673214726,
            0.1111190714683518
        ]
    },
    {
        "sub_start": 217.5,
        "sub_end": 420.0,
        "bestObjV": 826.7722909112769,
        "bestParams": [
            427.1147643129369,
            2.1056722817374913,
            0.689972480875412
        ]
    },
    {
        "sub_start": 239.25,
        "sub_end": 420.0,
        "bestObjV": 644.998109504465,
        "bestParams": [
            423.18837960026053,
            1.756178845627879,
            0.12351693258099511
        ]
    },
    {
        "sub_start": 261.0,
        "sub_end": 420.0,
        "bestObjV": 604.274904674609,
        "bestParams": [
            421.1800099895751,
            1.5020180353227444,
            0.3043813387212578
        ]
    },
    {
        "sub_start": 282.75,
        "sub_end": 420.0,
        "bestObjV": 463.2073758406679,
        "bestParams": [
            629.6630310628753,
            19.681322061802703,
            0.3340345419363291
        ]
    },
    {
        "sub_start": 304.5,
        "sub_end": 420.0,
        "bestObjV": 423.79626566825596,
        "bestParams": [
            897.1544372471599,
            40.0,
            0.626403892601377
        ]
    },
    {
        "sub_start": 0.0,
        "sub_end": 415.0,
        "bestObjV": 3550.176328356432,
        "bestParams": [
            2935.0,
            27.918132867750348,
            0.9
        ]
    },
    {
        "sub_start": 21.75,
        "sub_end": 415.0,
        "bestObjV": 3452.273057061561,
        "bestParams": [
            2935.0,
            25.002065616384684,
            0.9
        ]
    },
    {
        "sub_start": 43.5,
        "sub_end": 415.0,
        "bestObjV": 2899.85643981338,
        "bestParams": [
            419.74293850796386,
            0.23173844093225326,
            0.9
        ]
    },
    {
        "sub_start": 65.25,
        "sub_end": 415.0,
        "bestObjV": 2224.9201519995277,
        "bestParams": [
            2935.0,
            0.24949799475479373,
            0.9
        ]
    },
    {
        "sub_start": 87.0,
        "sub_end": 415.0,
        "bestObjV": 2038.4107089117174,
        "bestParams": [
            977.0041288457752,
            0.09922058577824067,
            0.9
        ]
    },
    {
        "sub_start": 108.75,
        "sub_end": 415.0,
        "bestObjV": 1380.2642310246413,
        "bestParams": [
            421.41485498704,
            0.13051458727494802,
            0.3430850202024254
        ]
    },
    {
        "sub_start": 130.5,
        "sub_end": 415.0,
        "bestObjV": 1357.30812500282,
        "bestParams": [
            415.1629605724631,
            1.1521788157150858,
            0.6426032497990812
        ]
    },
    {
        "sub_start": 152.25,
        "sub_end": 415.0,
        "bestObjV": 1283.5225469412405,
        "bestParams": [
            422.6230070265476,
            0.12120555114156595,
            0.1
        ]
    },
    {
        "sub_start": 174.0,
        "sub_end": 415.0,
        "bestObjV": 1154.7071904752177,
        "bestParams": [
            419.2099319985512,
            0.06587536168615737,
            0.29774578464360274
        ]
    },
    {
        "sub_start": 195.75,
        "sub_end": 415.0,
        "bestObjV": 875.5473082575302,
        "bestParams": [
            1035.5712501428977,
            17.589260642960923,
            0.5896838053077684
        ]
    },
    {
        "sub_start": 217.5,
        "sub_end": 415.0,
        "bestObjV": 662.1559802447684,
        "bestParams": [
            416.7754654846417,
            0.4223245011877408,
            0.5247240359842623
        ]
    },
    {
        "sub_start": 239.25,
        "sub_end": 415.0,
        "bestObjV": 599.2797567080477,
        "bestParams": [
            417.12635260300874,
            1.3667406480662163,
            0.1
        ]
    },
    {
        "sub_start": 261.0,
        "sub_end": 415.0,
        "bestObjV": 567.1635788562024,
        "bestParams": [
            432.1544430486451,
            3.8081293145269015,
            0.7332115674348568
        ]
    },
    {
        "sub_start": 282.75,
        "sub_end": 415.0,
        "bestObjV": 390.0135378729779,
        "bestParams": [
            622.2275430436782,
            18.167281050174918,
            0.33524370543306264
        ]
    },
    {
        "sub_start": 304.5,
        "sub_end": 415.0,
        "bestObjV": 359.318314877935,
        "bestParams": [
            925.5090172521908,
            40.0,
            0.8613433999639153
        ]
    },
    {
        "sub_start": 0.0,
        "sub_end": 410.0,
        "bestObjV": 3488.1487926938908,
        "bestParams": [
            2930.0,
            25.563189348232736,
            0.9
        ]
    },
    {
        "sub_start": 21.75,
        "sub_end": 410.0,
        "bestObjV": 3379.7545935929684,
        "bestParams": [
            2930.0,
            21.558393725220903,
            0.9
        ]
    },
    {
        "sub_start": 43.5,
        "sub_end": 410.0,
        "bestObjV": 2790.097757025525,
        "bestParams": [
            593.1775224867836,
            0.11599003419247089,
            0.9
        ]
    },
    {
        "sub_start": 65.25,
        "sub_end": 410.0,
        "bestObjV": 2170.5396489285695,
        "bestParams": [
            2913.1042531049984,
            0.37414549894990456,
            0.9
        ]
    },
    {
        "sub_start": 87.0,
        "sub_end": 410.0,
        "bestObjV": 1948.1895256965909,
        "bestParams": [
            523.7590085583614,
            0.024800888458659354,
            0.9
        ]
    },
    {
        "sub_start": 108.75,
        "sub_end": 410.0,
        "bestObjV": 1324.9739156450687,
        "bestParams": [
            431.1818489169114,
            0.071544674245126,
            0.5845790804815812
        ]
    },
    {
        "sub_start": 130.5,
        "sub_end": 410.0,
        "bestObjV": 1280.3296719559144,
        "bestParams": [
            415.6958719726699,
            0.1739704697870107,
            0.33943182247801074
        ]
    },
    {
        "sub_start": 152.25,
        "sub_end": 410.0,
        "bestObjV": 1256.465713839468,
        "bestParams": [
            419.0822231136208,
            0.18581046299094284,
            0.34142686649595955
        ]
    },
    {
        "sub_start": 174.0,
        "sub_end": 410.0,
        "bestObjV": 1066.3012026630627,
        "bestParams": [
            414.7637057679955,
            1.5498888993240092,
            0.12353873967124965
        ]
    },
    {
        "sub_start": 195.75,
        "sub_end": 410.0,
        "bestObjV": 702.7245192992625,
        "bestParams": [
            2930.0,
            25.200398686569475,
            0.9
        ]
    },
    {
        "sub_start": 217.5,
        "sub_end": 410.0,
        "bestObjV": 616.0706390555277,
        "bestParams": [
            420.5047074765235,
            1.103277319711033,
            0.10117982887688938
        ]
    },
    {
        "sub_start": 239.25,
        "sub_end": 410.0,
        "bestObjV": 592.091577448431,
        "bestParams": [
            412.2659655188599,
            0.9305014021833946,
            0.46758426034309797
        ]
    },
    {
        "sub_start": 261.0,
        "sub_end": 410.0,
        "bestObjV": 457.4405416277601,
        "bestParams": [
            415.9325934043383,
            3.2861841644504906,
            0.4534194302738572
        ]
    },
    {
        "sub_start": 282.75,
        "sub_end": 410.0,
        "bestObjV": 324.2525538117459,
        "bestParams": [
            830.5006062753941,
            29.188384248240602,
            0.2765108797923946
        ]
    },
    {
        "sub_start": 304.5,
        "sub_end": 410.0,
        "bestObjV": 297.4822337930156,
        "bestParams": [
            1010.1917013442213,
            40.0,
            0.7127803375569348
        ]
    }
]