[
    {
        "sub_start": 4361.0,
        "sub_end": 5551.0,
        "bestObjV": 17284.46247184607,
        "bestParams": [
            5590.683324178103,
            3.2533447892952383,
            0.16713282044050642
        ]
    },
    {
        "sub_start": 4420.5,
        "sub_end": 5551.0,
        "bestObjV": 19467.35029052407,
        "bestParams": [
            5553.150173478155,
            2.3347869682549804,
            0.4174448832787413
        ]
    },
    {
        "sub_start": 4480.0,
        "sub_end": 5551.0,
        "bestObjV": 16672.42077624432,
        "bestParams": [
            5628.45832583091,
            3.9559373591024727,
            0.12837674649761288
        ]
    },
    {
        "sub_start": 4539.5,
        "sub_end": 5551.0,
        "bestObjV": 16158.06626704178,
        "bestParams": [
            5666.892773400134,
            4.369307529048929,
            0.10715977360009994
        ]
    },
    {
        "sub_start": 4599.0,
        "sub_end": 5551.0,
        "bestObjV": 16006.743230599244,
        "bestParams": [
            5636.086269696409,
            3.972528179352093,
            0.10547204154069778
        ]
    },
    {
        "sub_start": 4658.5,
        "sub_end": 5551.0,
        "bestObjV": 15893.866187747699,
        "bestParams": [
            5654.2222953954015,
            4.1548415013987405,
            0.10929223938857709
        ]
    },
    {
        "sub_start": 4718.0,
        "sub_end": 5551.0,
        "bestObjV": 15661.76580402127,
        "bestParams": [
            5658.480625800354,
            4.1158541678434135,
            0.1160779385612476
        ]
    },
    {
        "sub_start": 4777.5,
        "sub_end": 5551.0,
        "bestObjV": 13006.635020516238,
        "bestParams": [
            5684.83465095043,
            4.470504999652283,
            0.20227688628089863
        ]
    },
    {
        "sub_start": 4837.0,
        "sub_end": 5551.0,
        "bestObjV": 13093.007022705486,
        "bestParams": [
            5785.636480081441,
            5.785238015788563,
            0.17110552429441572
        ]
    },
    {
        "sub_start": 4896.5,
        "sub_end": 5551.0,
        "bestObjV": 11914.274125001679,
        "bestParams": [
            5630.641552068663,
            3.7685485921969297,
            0.2913788980812785
        ]
    },
    {
        "sub_start": 4956.0,
        "sub_end": 5551.0,
        "bestObjV": 11217.017073688949,
        "bestParams": [
            5679.611703798761,
            4.569773111429778,
            0.12524933311824188
        ]
    },
    {
        "sub_start": 5015.5,
        "sub_end": 5551.0,
        "bestObjV": 7579.029913996965,
        "bestParams": [
            5721.517132917812,
            5.3370826100797775,
            0.8884103995695367
        ]
    },
    {
        "sub_start": 5075.0,
        "sub_end": 5551.0,
        "bestObjV": 7000.06449360232,
        "bestParams": [
            5802.84050140533,
            7.121246180727128,
            0.8546120199661309
        ]
    },
    {
        "sub_start": 5134.5,
        "sub_end": 5551.0,
        "bestObjV": 5225.850013231968,
        "bestParams": [
            5799.6281903994595,
            5.43849668714441,
            0.8981535123653125
        ]
    },
    {
        "sub_start": 5194.0,
        "sub_end": 5551.0,
        "bestObjV": 3674.6801310311557,
        "bestParams": [
            5802.118538892612,
            0.45287902856216533,
            0.8985897503296213
        ]
    },
    {
        "sub_start": 4361.0,
        "sub_end": 5546.0,
        "bestObjV": 16860.46526066749,
        "bestParams": [
            5626.860236552941,
            3.9928853773889994,
            0.14001186709559718
        ]
    },
    {
        "sub_start": 4420.5,
        "sub_end": 5546.0,
        "bestObjV": 16506.148623112098,
        "bestParams": [
            5650.313340092403,
            4.138923320750569,
            0.12467453507461733
        ]
    },
    {
        "sub_start": 4480.0,
        "sub_end": 5546.0,
        "bestObjV": 16415.220089371007,
        "bestParams": [
            5592.284269224788,
            3.305726232472308,
            0.20102393402179353
        ]
    },
    {
        "sub_start": 4539.5,
        "sub_end": 5546.0,
        "bestObjV": 16420.53491179339,
        "bestParams": [
            5587.4444735930265,
            3.17878763731001,
            0.23869351915350584
        ]
    },
    {
        "sub_start": 4599.0,
        "sub_end": 5546.0,
        "bestObjV": 18473.18711482154,
        "bestParams": [
            5741.703886180575,
            4.326495054024244,
            0.22037209489196485
        ]
    },
    {
        "sub_start": 4658.5,
        "sub_end": 5546.0,
        "bestObjV": 16371.483832707672,
        "bestParams": [
            5730.739345685619,
            5.310696781188486,
            0.10816930259655395
        ]
    },
    {
        "sub_start": 4718.0,
        "sub_end": 5546.0,
        "bestObjV": 18448.010039096713,
        "bestParams": [
            5701.074567557531,
            3.402308274879946,
            0.37521306153350253
        ]
    },
    {
        "sub_start": 4777.5,
        "sub_end": 5546.0,
        "bestObjV": 13041.930845852812,
        "bestParams": [
            5604.5754366170195,
            3.3673759026218253,
            0.41204731724994115
        ]
    },
    {
        "sub_start": 4837.0,
        "sub_end": 5546.0,
        "bestObjV": 12619.8681147616,
        "bestParams": [
            5688.705474363963,
            4.721517348903879,
            0.17132129126668483
        ]
    },
    {
        "sub_start": 4896.5,
        "sub_end": 5546.0,
        "bestObjV": 11894.110132260626,
        "bestParams": [
            5783.312823470034,
            6.0752005329911185,
            0.1020913123268053
        ]
    },
    {
        "sub_start": 4956.0,
        "sub_end": 5546.0,
        "bestObjV": 11135.720260471966,
        "bestParams": [
            5777.4138411160575,
            6.086671493701101,
            0.11748040705641963
        ]
    },
    {
        "sub_start": 5015.5,
        "sub_end": 5546.0,
        "bestObjV": 7333.558622953265,
        "bestParams": [
            5771.103363516039,
            6.1782959544784255,
            0.8995345506120879
        ]
    },
    {
        "sub_start": 5075.0,
        "sub_end": 5546.0,
        "bestObjV": 6841.274996417863,
        "bestParams": [
            5789.5448119067205,
            6.7382775633375225,
            0.8962344082264203
        ]
    },
    {
        "sub_start": 5134.5,
        "sub_end": 5546.0,
        "bestObjV": 5189.956684989074,
        "bestParams": [
            5791.599352339482,
            5.4268435962795225,
            0.8942777422908404
        ]
    },
    {
        "sub_start": 5194.0,
        "sub_end": 5546.0,
        "bestObjV": 3766.8011565855604,
        "bestParams": [
            5777.359049491168,
            2.625489931000309,
            0.8830825399813527
        ]
    },
    {
        "sub_start": 4361.0,
        "sub_end": 5541.0,
        "bestObjV": 16627.4210726303,
        "bestParams": [
            5647.567780215045,
            4.067785613050319,
            0.12750284458704897
        ]
    },
    {
        "sub_start": 4420.5,
        "sub_end": 5541.0,
        "bestObjV": 17167.80711568502,
        "bestParams": [
            5624.975596066968,
            4.0482852721536355,
            0.21174380677826676
        ]
    },
    {
        "sub_start": 4480.0,
        "sub_end": 5541.0,
        "bestObjV": 16729.77279636169,
        "bestParams": [
            5708.250656518365,
            4.783318929676907,
            0.10446273164881328
        ]
    },
    {
        "sub_start": 4539.5,
        "sub_end": 5541.0,
        "bestObjV": 17041.970019825392,
        "bestParams": [
            5763.005218264723,
            5.709549528775595,
            0.1061195194847982
        ]
    },
    {
        "sub_start": 4599.0,
        "sub_end": 5541.0,
        "bestObjV": 15861.35219704372,
        "bestParams": [
            5647.899369510273,
            4.313551149252062,
            0.10476462245367141
        ]
    },
    {
        "sub_start": 4658.5,
        "sub_end": 5541.0,
        "bestObjV": 15772.38246979267,
        "bestParams": [
            5667.540721139128,
            4.514386168912288,
            0.10552637171930926
        ]
    },
    {
        "sub_start": 4718.0,
        "sub_end": 5541.0,
        "bestObjV": 15799.182964130236,
        "bestParams": [
            5591.5663937297,
            3.2501688976355902,
            0.22880721389011305
        ]
    },
    {
        "sub_start": 4777.5,
        "sub_end": 5541.0,
        "bestObjV": 12924.359942962086,
        "bestParams": [
            5633.24745703259,
            3.8921828838989914,
            0.291717216256541
        ]
    },
    {
        "sub_start": 4837.0,
        "sub_end": 5541.0,
        "bestObjV": 12547.889866149952,
        "bestParams": [
            5641.880753462513,
            4.157356173137554,
            0.10785721735870642
        ]
    },
    {
        "sub_start": 4896.5,
        "sub_end": 5541.0,
        "bestObjV": 11627.07924813088,
        "bestParams": [
            5674.555397857383,
            4.557707812137903,
            0.10132518202337347
        ]
    },
    {
        "sub_start": 4956.0,
        "sub_end": 5541.0,
        "bestObjV": 11493.120017653904,
        "bestParams": [
            5579.160622517543,
            2.880365666429685,
            0.5979683687733143
        ]
    },
    {
        "sub_start": 5015.5,
        "sub_end": 5541.0,
        "bestObjV": 7548.675972791372,
        "bestParams": [
            5701.517650222645,
            5.03421303102872,
            0.8942812122836695
        ]
    },
    {
        "sub_start": 5075.0,
        "sub_end": 5541.0,
        "bestObjV": 7274.501400008176,
        "bestParams": [
            5686.0349258847245,
            4.929744825048128,
            0.8977576007596623
        ]
    },
    {
        "sub_start": 5134.5,
        "sub_end": 5541.0,
        "bestObjV": 5290.973136706543,
        "bestParams": [
            5576.065644949776,
            0.050068506216924824,
            0.19718394212588075
        ]
    },
    {
        "sub_start": 5194.0,
        "sub_end": 5541.0,
        "bestObjV": 3602.7757978882946,
        "bestParams": [
            5791.0692934467625,
            0.22507958087063962,
            0.896075992506964
        ]
    },
    {
        "sub_start": 4361.0,
        "sub_end": 5536.0,
        "bestObjV": 16588.05502760148,
        "bestParams": [
            5624.660596563862,
            3.8194890049904373,
            0.1484920463391271
        ]
    },
    {
        "sub_start": 4420.5,
        "sub_end": 5536.0,
        "bestObjV": 16439.978285015037,
        "bestParams": [
            5640.327952993124,
            3.985149974206106,
            0.1324862872634773
        ]
    },
    {
        "sub_start": 4480.0,
        "sub_end": 5536.0,
        "bestObjV": 16270.817446292689,
        "bestParams": [
            5629.394974351526,
            3.844863636327127,
            0.14693453036336807
        ]
    },
    {
        "sub_start": 4539.5,
        "sub_end": 5536.0,
        "bestObjV": 16510.987713651182,
        "bestParams": [
            5575.338827392702,
            2.9868160378493114,
            0.24439089483220125
        ]
    },
    {
        "sub_start": 4599.0,
        "sub_end": 5536.0,
        "bestObjV": 16554.948538095774,
        "bestParams": [
            5569.330843318769,
            2.883047078103136,
            0.2640027729811517
        ]
    },
    {
        "sub_start": 4658.5,
        "sub_end": 5536.0,
        "bestObjV": 15660.146943616004,
        "bestParams": [
            5645.482635249123,
            4.211751666128349,
            0.1066810881087637
        ]
    },
    {
        "sub_start": 4718.0,
        "sub_end": 5536.0,
        "bestObjV": 15684.345746881474,
        "bestParams": [
            5590.65473287337,
            3.3230691973923454,
            0.17074422177578913
        ]
    },
    {
        "sub_start": 4777.5,
        "sub_end": 5536.0,
        "bestObjV": 12827.086066574298,
        "bestParams": [
            5677.4725462768665,
            4.552257020418726,
            0.15069412172218302
        ]
    },
    {
        "sub_start": 4837.0,
        "sub_end": 5536.0,
        "bestObjV": 13338.184569155994,
        "bestParams": [
            5592.623772107135,
            2.661206100460274,
            0.684347910610198
        ]
    },
    {
        "sub_start": 4896.5,
        "sub_end": 5536.0,
        "bestObjV": 11627.881159218006,
        "bestParams": [
            5711.805208940684,
            5.017718361244996,
            0.10819962724410459
        ]
    },
    {
        "sub_start": 4956.0,
        "sub_end": 5536.0,
        "bestObjV": 11199.104606503275,
        "bestParams": [
            5632.29163256973,
            3.9784802774555494,
            0.22988976859011992
        ]
    },
    {
        "sub_start": 5015.5,
        "sub_end": 5536.0,
        "bestObjV": 7340.78657859628,
        "bestParams": [
            5776.426865320697,
            6.476971972596317,
            0.8680206703465402
        ]
    },
    {
        "sub_start": 5075.0,
        "sub_end": 5536.0,
        "bestObjV": 6984.863431987668,
        "bestParams": [
            5746.184394151453,
            5.902508954689627,
            0.8982991633982818
        ]
    },
    {
        "sub_start": 5134.5,
        "sub_end": 5536.0,
        "bestObjV": 5158.514460891904,
        "bestParams": [
            5738.282887368259,
            4.394271720739451,
            0.862734756215202
        ]
    },
    {
        "sub_start": 5194.0,
        "sub_end": 5536.0,
        "bestObjV": 3546.226715447739,
        "bestParams": [
            5787.4286881107,
            0.21455808125223186,
            0.8980954092739529
        ]
    },
    {
        "sub_start": 4361.0,
        "sub_end": 5531.0,
        "bestObjV": 16883.312638497584,
        "bestParams": [
            5585.532868034258,
            3.3036073692447765,
            0.17583900569390096
        ]
    },
    {
        "sub_start": 4420.5,
        "sub_end": 5531.0,
        "bestObjV": 16286.49789770195,
        "bestParams": [
            5650.8076562306005,
            4.036219673819548,
            0.10042320810398514
        ]
    },
    {
        "sub_start": 4480.0,
        "sub_end": 5531.0,
        "bestObjV": 16149.644407614887,
        "bestParams": [
            5622.781198006913,
            3.6505357509092518,
            0.15024904887335788
        ]
    },
    {
        "sub_start": 4539.5,
        "sub_end": 5531.0,
        "bestObjV": 15897.536022683515,
        "bestParams": [
            5662.781408821696,
            4.349454121379792,
            0.10403538680965303
        ]
    },
    {
        "sub_start": 4599.0,
        "sub_end": 5531.0,
        "bestObjV": 16086.204848811256,
        "bestParams": [
            5597.861291330178,
            3.318040783193439,
            0.187603858456192
        ]
    },
    {
        "sub_start": 4658.5,
        "sub_end": 5531.0,
        "bestObjV": 15641.399628692261,
        "bestParams": [
            5619.996030666086,
            3.7635726672961356,
            0.10982113743333369
        ]
    },
    {
        "sub_start": 4718.0,
        "sub_end": 5531.0,
        "bestObjV": 17967.132432836643,
        "bestParams": [
            5670.6757803953315,
            2.2778064200531434,
            0.2672580598789698
        ]
    },
    {
        "sub_start": 4777.5,
        "sub_end": 5531.0,
        "bestObjV": 13111.701943026637,
        "bestParams": [
            5595.890121185752,
            2.821831741750054,
            0.6162078539764968
        ]
    },
    {
        "sub_start": 4837.0,
        "sub_end": 5531.0,
        "bestObjV": 12441.978091780487,
        "bestParams": [
            5648.334990108012,
            4.047945802291082,
            0.15307578804438615
        ]
    },
    {
        "sub_start": 4896.5,
        "sub_end": 5531.0,
        "bestObjV": 11625.379839541498,
        "bestParams": [
            5644.280216682856,
            4.0085422756317035,
            0.292842811760721
        ]
    },
    {
        "sub_start": 4956.0,
        "sub_end": 5531.0,
        "bestObjV": 11103.503722120444,
        "bestParams": [
            5646.586284276962,
            3.8337904859190886,
            0.3320716421116996
        ]
    },
    {
        "sub_start": 5015.5,
        "sub_end": 5531.0,
        "bestObjV": 7271.15995432229,
        "bestParams": [
            5751.821193787728,
            5.57833818865328,
            0.8929125220094246
        ]
    },
    {
        "sub_start": 5075.0,
        "sub_end": 5531.0,
        "bestObjV": 6910.779817951098,
        "bestParams": [
            5742.007976613269,
            5.719660287879429,
            0.8999111787941433
        ]
    },
    {
        "sub_start": 5134.5,
        "sub_end": 5531.0,
        "bestObjV": 4927.014374349274,
        "bestParams": [
            5778.649448569639,
            4.2792003719584715,
            0.8845373805559663
        ]
    },
    {
        "sub_start": 5194.0,
        "sub_end": 5531.0,
        "bestObjV": 3334.312259252338,
        "bestParams": [
            5770.73422339734,
            0.5960729218642458,
            0.8755370858084077
        ]
    },
    {
        "sub_start": 4361.0,
        "sub_end": 5526.0,
        "bestObjV": 17463.575367848396,
        "bestParams": [
            5738.059723233131,
            5.066062423764626,
            0.1432897487854545
        ]
    },
    {
        "sub_start": 4420.5,
        "sub_end": 5526.0,
        "bestObjV": 16387.14304274455,
        "bestParams": [
            5674.346218224551,
            4.135991899590996,
            0.10079509846076445
        ]
    },
    {
        "sub_start": 4480.0,
        "sub_end": 5526.0,
        "bestObjV": 16719.405510310135,
        "bestParams": [
            5569.70880009595,
            2.7714166882220814,
            0.2642633147224478
        ]
    },
    {
        "sub_start": 4539.5,
        "sub_end": 5526.0,
        "bestObjV": 16204.135195226536,
        "bestParams": [
            5700.4180725714305,
            4.8701777120199985,
            0.10423074349596764
        ]
    },
    {
        "sub_start": 4599.0,
        "sub_end": 5526.0,
        "bestObjV": 16155.328960139106,
        "bestParams": [
            5590.398704294299,
            3.145211830432566,
            0.192386746582243
        ]
    },
    {
        "sub_start": 4658.5,
        "sub_end": 5526.0,
        "bestObjV": 16353.919018138477,
        "bestParams": [
            5672.421944125909,
            3.5156774331664087,
            0.12813176207371743
        ]
    },
    {
        "sub_start": 4718.0,
        "sub_end": 5526.0,
        "bestObjV": 15602.83229177839,
        "bestParams": [
            5594.714362182038,
            3.2569391940754455,
            0.16828403167495712
        ]
    },
    {
        "sub_start": 4777.5,
        "sub_end": 5526.0,
        "bestObjV": 12544.3227566647,
        "bestParams": [
            5724.840419021866,
            4.830933169463805,
            0.10138829525126863
        ]
    },
    {
        "sub_start": 4837.0,
        "sub_end": 5526.0,
        "bestObjV": 12587.706114541761,
        "bestParams": [
            5620.295937696381,
            3.237302635684478,
            0.4015450391998877
        ]
    },
    {
        "sub_start": 4896.5,
        "sub_end": 5526.0,
        "bestObjV": 11367.870265949041,
        "bestParams": [
            5717.8810171335845,
            4.788025292740867,
            0.1053918297233853
        ]
    },
    {
        "sub_start": 4956.0,
        "sub_end": 5526.0,
        "bestObjV": 10955.417505870779,
        "bestParams": [
            5674.321459086507,
            4.264272655660699,
            0.3415725783185106
        ]
    },
    {
        "sub_start": 5015.5,
        "sub_end": 5526.0,
        "bestObjV": 7229.830841442423,
        "bestParams": [
            5756.630983885328,
            5.46107216040026,
            0.866317557712745
        ]
    },
    {
        "sub_start": 5075.0,
        "sub_end": 5526.0,
        "bestObjV": 6739.510860911478,
        "bestParams": [
            5777.340660955512,
            6.132907641857175,
            0.897739342963319
        ]
    },
    {
        "sub_start": 5134.5,
        "sub_end": 5526.0,
        "bestObjV": 4780.120953676929,
        "bestParams": [
            5777.142606004945,
            3.625440658722363,
            0.8987368129560623
        ]
    },
    {
        "sub_start": 5194.0,
        "sub_end": 5526.0,
        "bestObjV": 3187.6700951975013,
        "bestParams": [
            5769.601579459652,
            0.16343203758680147,
            0.892185958011584
        ]
    }
]