[
    {
        "sub_start": 1273.0,
        "sub_end": 2343.0,
        "bestObjV": 9202.593630327032,
        "bestParams": [
            2683.2512512005947,
            9.791196576978875,
            5.006409770048972,
            0.35560740719159645
        ]
    },
    {
        "sub_start": 1326.5,
        "sub_end": 2343.0,
        "bestObjV": 9093.547233503792,
        "bestParams": [
            4162.837413609279,
            1.2577633933365098,
            0.43191469167281227,
            0.4036971602731782
        ]
    },
    {
        "sub_start": 1380.0,
        "sub_end": 2343.0,
        "bestObjV": 6920.128793225501,
        "bestParams": [
            4389.203759966122,
            22.517316531376572,
            3.966102663765718,
            0.19263200412651538
        ]
    },
    {
        "sub_start": 1433.5,
        "sub_end": 2343.0,
        "bestObjV": 5547.2822907253085,
        "bestParams": [
            2934.9669646920006,
            17.89030723004737,
            1.37642219720852,
            0.1
        ]
    },
    {
        "sub_start": 1487.0,
        "sub_end": 2343.0,
        "bestObjV": 5289.970322585454,
        "bestParams": [
            3743.3015678849124,
            18.26392333876584,
            0.9821293622489613,
            0.7414823595715528
        ]
    },
    {
        "sub_start": 1540.5,
        "sub_end": 2343.0,
        "bestObjV": 4456.964590912532,
        "bestParams": [
            4556.9287694732575,
            10.275444577293595,
            6.283185307179586,
            0.581081847197232
        ]
    },
    {
        "sub_start": 1594.0,
        "sub_end": 2343.0,
        "bestObjV": 3797.6428539369463,
        "bestParams": [
            2983.465001151978,
            0.0,
            0.31917873724347856,
            0.5618913015488729
        ]
    },
    {
        "sub_start": 1647.5,
        "sub_end": 2343.0,
        "bestObjV": 3196.3400370008007,
        "bestParams": [
            3736.650629144256,
            7.191783411183242,
            2.1017007304589916,
            0.9
        ]
    },
    {
        "sub_start": 1701.0,
        "sub_end": 2343.0,
        "bestObjV": 3838.8567417899435,
        "bestParams": [
            3232.599750606668,
            25.967766755229476,
            4.094633958096926,
            0.4925034103824915
        ]
    },
    {
        "sub_start": 1754.5,
        "sub_end": 2343.0,
        "bestObjV": 2651.379167945454,
        "bestParams": [
            4643.753698966089,
            24.820094551361677,
            0.5028676221470822,
            0.43671247472683133
        ]
    },
    {
        "sub_start": 1808.0,
        "sub_end": 2343.0,
        "bestObjV": 1519.7400190353615,
        "bestParams": [
            4692.986523881405,
            5.737427590483812,
            0.8269705457117877,
            0.342500897938965
        ]
    },
    {
        "sub_start": 1861.5,
        "sub_end": 2343.0,
        "bestObjV": 1055.8860923014463,
        "bestParams": [
            2759.5726550949903,
            29.510785391546914,
            4.95972142221306,
            0.5442646686755956
        ]
    },
    {
        "sub_start": 1915.0,
        "sub_end": 2343.0,
        "bestObjV": 853.567837813865,
        "bestParams": [
            2343.0,
            11.569158016188092,
            4.026595126516584,
            0.15806459766101277
        ]
    },
    {
        "sub_start": 1968.5,
        "sub_end": 2343.0,
        "bestObjV": 422.2103170567401,
        "bestParams": [
            2674.3106445495587,
            31.93505123949429,
            2.345573305911333,
            0.16839432779907546
        ]
    },
    {
        "sub_start": 2022.0,
        "sub_end": 2343.0,
        "bestObjV": 406.98728683176955,
        "bestParams": [
            2859.7026637518525,
            6.484732464494601,
            1.1441071950096746,
            0.6079372438870843
        ]
    },
    {
        "sub_start": 1273.0,
        "sub_end": 2338.0,
        "bestObjV": 8962.661686336309,
        "bestParams": [
            3521.343090881187,
            27.9124985532183,
            2.380489076979993,
            0.4963346942206966
        ]
    },
    {
        "sub_start": 1326.5,
        "sub_end": 2338.0,
        "bestObjV": 9492.49728503685,
        "bestParams": [
            4535.275510330203,
            18.105469316253615,
            6.283185307179586,
            0.7305398360795041
        ]
    },
    {
        "sub_start": 1380.0,
        "sub_end": 2338.0,
        "bestObjV": 7711.621804802111,
        "bestParams": [
            4691.08761020923,
            0.0,
            2.2530749635802727,
            0.8174916551664536
        ]
    },
    {
        "sub_start": 1433.5,
        "sub_end": 2338.0,
        "bestObjV": 5557.821549361596,
        "bestParams": [
            4044.55588736145,
            34.42828381769424,
            2.9054576125274747,
            0.76566551736394
        ]
    },
    {
        "sub_start": 1487.0,
        "sub_end": 2338.0,
        "bestObjV": 4668.096026235577,
        "bestParams": [
            4201.282610017488,
            13.680760011407479,
            0.0,
            0.2284537886763694
        ]
    },
    {
        "sub_start": 1540.5,
        "sub_end": 2338.0,
        "bestObjV": 4672.0374289838155,
        "bestParams": [
            2920.9508195948156,
            40.0,
            2.103998410031703,
            0.5906716178337034
        ]
    },
    {
        "sub_start": 1594.0,
        "sub_end": 2338.0,
        "bestObjV": 3922.8992202678587,
        "bestParams": [
            4858.0,
            22.984425108238145,
            0.1480914630683503,
            0.7435293058684806
        ]
    },
    {
        "sub_start": 1647.5,
        "sub_end": 2338.0,
        "bestObjV": 4060.4902460592784,
        "bestParams": [
            3341.5793044348516,
            39.042270922228724,
            3.2496154566638893,
            0.522765290924121
        ]
    },
    {
        "sub_start": 1701.0,
        "sub_end": 2338.0,
        "bestObjV": 2643.4891638114855,
        "bestParams": [
            2780.5351802892,
            39.83642758617147,
            0.0,
            0.21854632861785078
        ]
    },
    {
        "sub_start": 1754.5,
        "sub_end": 2338.0,
        "bestObjV": 2942.77460762568,
        "bestParams": [
            4858.0,
            18.519198977027862,
            6.283185307179586,
            0.7741567430481084
        ]
    },
    {
        "sub_start": 1808.0,
        "sub_end": 2338.0,
        "bestObjV": 1339.280469432902,
        "bestParams": [
            3684.24851434811,
            25.192790786978005,
            1.8680340341955703,
            0.46967158385415975
        ]
    },
    {
        "sub_start": 1861.5,
        "sub_end": 2338.0,
        "bestObjV": 610.0086278336577,
        "bestParams": [
            4376.033196128245,
            0.0,
            3.2028808532774464,
            0.5403815282393902
        ]
    },
    {
        "sub_start": 1915.0,
        "sub_end": 2338.0,
        "bestObjV": 536.5123736356517,
        "bestParams": [
            3273.8965360206457,
            29.51245468555028,
            2.4632789651248164,
            0.20378192350235316
        ]
    },
    {
        "sub_start": 1968.5,
        "sub_end": 2338.0,
        "bestObjV": 404.0476191447179,
        "bestParams": [
            3073.826431793776,
            12.334517787124087,
            0.0,
            0.7720081316405502
        ]
    },
    {
        "sub_start": 2022.0,
        "sub_end": 2338.0,
        "bestObjV": 397.6134898473781,
        "bestParams": [
            4269.718426203604,
            6.3429512628442675,
            2.3643576918738205,
            0.9
        ]
    },
    {
        "sub_start": 1273.0,
        "sub_end": 2333.0,
        "bestObjV": 9150.883368156416,
        "bestParams": [
            4323.652955904059,
            28.905863418072663,
            6.283185307179586,
            0.6470967489919651
        ]
    },
    {
        "sub_start": 1326.5,
        "sub_end": 2333.0,
        "bestObjV": 9168.321667029124,
        "bestParams": [
            2333.0,
            40.0,
            3.60979232197626,
            0.2763836365903374
        ]
    },
    {
        "sub_start": 1380.0,
        "sub_end": 2333.0,
        "bestObjV": 7486.759911407145,
        "bestParams": [
            3160.3328693868034,
            15.86609340009171,
            1.8981334265126941,
            0.19369133083714932
        ]
    },
    {
        "sub_start": 1433.5,
        "sub_end": 2333.0,
        "bestObjV": 4829.367957017186,
        "bestParams": [
            4567.246068406353,
            34.39842938323823,
            0.0,
            0.5417636559453499
        ]
    },
    {
        "sub_start": 1487.0,
        "sub_end": 2333.0,
        "bestObjV": 5399.093107649796,
        "bestParams": [
            3249.976847619784,
            19.739829729265505,
            0.5354480858996487,
            0.2726815143276057
        ]
    },
    {
        "sub_start": 1540.5,
        "sub_end": 2333.0,
        "bestObjV": 4461.623857043185,
        "bestParams": [
            2556.072769462348,
            0.0,
            4.61910936691655,
            0.8645085278899313
        ]
    },
    {
        "sub_start": 1594.0,
        "sub_end": 2333.0,
        "bestObjV": 4046.1078450419095,
        "bestParams": [
            4089.093683074969,
            20.739124579089907,
            4.375508023569358,
            0.7394334956558981
        ]
    },
    {
        "sub_start": 1647.5,
        "sub_end": 2333.0,
        "bestObjV": 3590.8347369508892,
        "bestParams": [
            3441.498638733032,
            17.0587288245686,
            0.0,
            0.20347014304889524
        ]
    },
    {
        "sub_start": 1701.0,
        "sub_end": 2333.0,
        "bestObjV": 3497.700813831789,
        "bestParams": [
            4539.15222554609,
            16.724266203733812,
            3.432953290507128,
            0.5365390251984575
        ]
    },
    {
        "sub_start": 1754.5,
        "sub_end": 2333.0,
        "bestObjV": 2126.527597890443,
        "bestParams": [
            4318.056661770539,
            32.33251980063715,
            5.435751350008433,
            0.5649636958575293
        ]
    },
    {
        "sub_start": 1808.0,
        "sub_end": 2333.0,
        "bestObjV": 1758.8788682830038,
        "bestParams": [
            4777.55132028077,
            23.975621662718815,
            5.204910929668975,
            0.1
        ]
    },
    {
        "sub_start": 1861.5,
        "sub_end": 2333.0,
        "bestObjV": 812.9957853104161,
        "bestParams": [
            2333.0,
            22.137632525869634,
            5.171071719440412,
            0.7931543206875088
        ]
    },
    {
        "sub_start": 1915.0,
        "sub_end": 2333.0,
        "bestObjV": 478.32995566084554,
        "bestParams": [
            3977.985597567357,
            40.0,
            4.5861608088806225,
            0.6030855375590789
        ]
    },
    {
        "sub_start": 1968.5,
        "sub_end": 2333.0,
        "bestObjV": 426.30017676590535,
        "bestParams": [
            2333.0,
            22.233635462436133,
            5.922786482186567,
            0.31503503620147344
        ]
    },
    {
        "sub_start": 2022.0,
        "sub_end": 2333.0,
        "bestObjV": 426.7039364139618,
        "bestParams": [
            4144.086465942388,
            31.393562289330674,
            3.913339529540484,
            0.8810280646694806
        ]
    },
    {
        "sub_start": 1273.0,
        "sub_end": 2328.0,
        "bestObjV": 9673.091763120825,
        "bestParams": [
            4246.297092876968,
            0.0,
            2.1481866231715996,
            0.3158996552689875
        ]
    },
    {
        "sub_start": 1326.5,
        "sub_end": 2328.0,
        "bestObjV": 9289.733355609806,
        "bestParams": [
            3776.2695580438517,
            0.31762388927912616,
            3.735867374047368,
            0.9
        ]
    },
    {
        "sub_start": 1380.0,
        "sub_end": 2328.0,
        "bestObjV": 8109.68752977131,
        "bestParams": [
            4848.0,
            19.45526829677251,
            1.9006645093753995,
            0.3165799456632489
        ]
    },
    {
        "sub_start": 1433.5,
        "sub_end": 2328.0,
        "bestObjV": 5508.291154352873,
        "bestParams": [
            2874.735379745458,
            20.207429515707698,
            3.302996133920692,
            0.9
        ]
    },
    {
        "sub_start": 1487.0,
        "sub_end": 2328.0,
        "bestObjV": 5077.416636189504,
        "bestParams": [
            4610.042633783529,
            22.834458267250614,
            3.068611127889236,
            0.1
        ]
    },
    {
        "sub_start": 1540.5,
        "sub_end": 2328.0,
        "bestObjV": 4549.278205125795,
        "bestParams": [
            3000.599384093421,
            22.772208352518845,
            5.778360621518743,
            0.5400750505474069
        ]
    },
    {
        "sub_start": 1594.0,
        "sub_end": 2328.0,
        "bestObjV": 3117.26084923181,
        "bestParams": [
            4533.875842868873,
            11.005535796667736,
            1.2518701739094766,
            0.5721399488266582
        ]
    },
    {
        "sub_start": 1647.5,
        "sub_end": 2328.0,
        "bestObjV": 3619.475971830466,
        "bestParams": [
            4848.0,
            12.386652567894272,
            5.87913154858337,
            0.2600090336252571
        ]
    },
    {
        "sub_start": 1701.0,
        "sub_end": 2328.0,
        "bestObjV": 3339.3390420762903,
        "bestParams": [
            4187.174800152073,
            38.698839538626686,
            0.0,
            0.6282849438486942
        ]
    },
    {
        "sub_start": 1754.5,
        "sub_end": 2328.0,
        "bestObjV": 2610.1381670478495,
        "bestParams": [
            4264.8391188224,
            30.162900346698635,
            0.0,
            0.20172609015900167
        ]
    },
    {
        "sub_start": 1808.0,
        "sub_end": 2328.0,
        "bestObjV": 1837.868608754652,
        "bestParams": [
            3066.0242430718945,
            17.678774903708597,
            4.694306675559387,
            0.8619346226441118
        ]
    },
    {
        "sub_start": 1861.5,
        "sub_end": 2328.0,
        "bestObjV": 601.7187273025311,
        "bestParams": [
            4848.0,
            16.151573306994376,
            2.2565881930809146,
            0.2839808141124421
        ]
    },
    {
        "sub_start": 1915.0,
        "sub_end": 2328.0,
        "bestObjV": 750.8966106491852,
        "bestParams": [
            4721.699699515614,
            38.40155587690367,
            0.5951884938192622,
            0.2029816878414416
        ]
    },
    {
        "sub_start": 1968.5,
        "sub_end": 2328.0,
        "bestObjV": 399.91720604703386,
        "bestParams": [
            2429.5847624007292,
            19.850604867902888,
            2.171841698766273,
            0.6248602243612387
        ]
    },
    {
        "sub_start": 2022.0,
        "sub_end": 2328.0,
        "bestObjV": 362.07297019208613,
        "bestParams": [
            3627.4617986027497,
            30.213550317403456,
            4.843765558590645,
            0.883769276203872
        ]
    },
    {
        "sub_start": 1273.0,
        "sub_end": 2323.0,
        "bestObjV": 9495.138884030152,
        "bestParams": [
            3811.741722179723,
            23.79623676272267,
            1.7298919032719555,
            0.4197121023141691
        ]
    },
    {
        "sub_start": 1326.5,
        "sub_end": 2323.0,
        "bestObjV": 8679.49878933589,
        "bestParams": [
            4524.2017121275485,
            14.431905987796632,
            3.074490307164021,
            0.6301193017659372
        ]
    },
    {
        "sub_start": 1380.0,
        "sub_end": 2323.0,
        "bestObjV": 7059.67489898232,
        "bestParams": [
            3503.845450520953,
            9.555921536641758,
            1.3313615991606014,
            0.681496574976234
        ]
    },
    {
        "sub_start": 1433.5,
        "sub_end": 2323.0,
        "bestObjV": 4594.175722938534,
        "bestParams": [
            4271.486309825714,
            21.61397104185648,
            4.887380725544622,
            0.9
        ]
    },
    {
        "sub_start": 1487.0,
        "sub_end": 2323.0,
        "bestObjV": 4367.382293878641,
        "bestParams": [
            2676.027008220638,
            16.473975644214526,
            3.131643916695359,
            0.41694467172629707
        ]
    },
    {
        "sub_start": 1540.5,
        "sub_end": 2323.0,
        "bestObjV": 3116.73378328881,
        "bestParams": [
            4588.11429350374,
            18.188929994827255,
            0.0,
            0.5316016197851774
        ]
    },
    {
        "sub_start": 1594.0,
        "sub_end": 2323.0,
        "bestObjV": 3106.775021171998,
        "bestParams": [
            3290.6467152812975,
            40.0,
            0.0,
            0.8997637574684365
        ]
    },
    {
        "sub_start": 1647.5,
        "sub_end": 2323.0,
        "bestObjV": 2960.8407464644665,
        "bestParams": [
            2510.6766279548287,
            36.075448052838375,
            6.2277305197943935,
            0.703835894110186
        ]
    },
    {
        "sub_start": 1701.0,
        "sub_end": 2323.0,
        "bestObjV": 2655.827138173372,
        "bestParams": [
            2836.9893088713347,
            3.701757839175312,
            1.2009475124317714,
            0.37544100498936595
        ]
    },
    {
        "sub_start": 1754.5,
        "sub_end": 2323.0,
        "bestObjV": 3054.6284522898727,
        "bestParams": [
            3054.6215946867983,
            36.47114679231072,
            0.0,
            0.32996651981891173
        ]
    },
    {
        "sub_start": 1808.0,
        "sub_end": 2323.0,
        "bestObjV": 1661.438906912113,
        "bestParams": [
            2843.864053178151,
            14.511220204562793,
            2.9599509279663034,
            0.23799566664198252
        ]
    },
    {
        "sub_start": 1861.5,
        "sub_end": 2323.0,
        "bestObjV": 555.3462186697617,
        "bestParams": [
            3496.2257150351893,
            23.318188176812427,
            4.23028736220664,
            0.678726979192375
        ]
    },
    {
        "sub_start": 1915.0,
        "sub_end": 2323.0,
        "bestObjV": 482.0594934890234,
        "bestParams": [
            4578.94342830159,
            26.040819816176164,
            6.283185307179586,
            0.8760330551680984
        ]
    },
    {
        "sub_start": 1968.5,
        "sub_end": 2323.0,
        "bestObjV": 439.70389211019506,
        "bestParams": [
            3741.023526028636,
            31.28602531167939,
            0.48808560979573745,
            0.5147641406253213
        ]
    },
    {
        "sub_start": 2022.0,
        "sub_end": 2323.0,
        "bestObjV": 355.0085386212203,
        "bestParams": [
            2464.2772761653946,
            11.908166509529476,
            6.283185307179586,
            0.5842303303608526
        ]
    },
    {
        "sub_start": 1273.0,
        "sub_end": 2318.0,
        "bestObjV": 9009.657726016789,
        "bestParams": [
            4838.0,
            40.0,
            5.750750457596844,
            0.44193596785115336
        ]
    },
    {
        "sub_start": 1326.5,
        "sub_end": 2318.0,
        "bestObjV": 10088.552360586978,
        "bestParams": [
            2986.9685103674997,
            25.99677706725426,
            2.253193458765866,
            0.548369449688642
        ]
    },
    {
        "sub_start": 1380.0,
        "sub_end": 2318.0,
        "bestObjV": 6651.014439946519,
        "bestParams": [
            3135.1175769274714,
            4.617896228690039,
            6.283185307179586,
            0.15178436346160523
        ]
    },
    {
        "sub_start": 1433.5,
        "sub_end": 2318.0,
        "bestObjV": 4385.693776745685,
        "bestParams": [
            4838.0,
            24.418295272710168,
            5.664523846833549,
            0.669513428429559
        ]
    },
    {
        "sub_start": 1487.0,
        "sub_end": 2318.0,
        "bestObjV": 4827.716403316141,
        "bestParams": [
            2902.0952709304674,
            17.29590143281426,
            5.994897427004383,
            0.6613329970483846
        ]
    },
    {
        "sub_start": 1540.5,
        "sub_end": 2318.0,
        "bestObjV": 4175.877760818862,
        "bestParams": [
            3117.3281319193443,
            31.03004176009087,
            5.770218076644222,
            0.5713646113853125
        ]
    },
    {
        "sub_start": 1594.0,
        "sub_end": 2318.0,
        "bestObjV": 3761.341735495392,
        "bestParams": [
            4812.588099740559,
            14.983642020321676,
            4.396090796133401,
            0.7270480481354669
        ]
    },
    {
        "sub_start": 1647.5,
        "sub_end": 2318.0,
        "bestObjV": 3779.8829274764894,
        "bestParams": [
            4653.905835375173,
            15.829879862404137,
            2.161934010719793,
            0.846845895003977
        ]
    },
    {
        "sub_start": 1701.0,
        "sub_end": 2318.0,
        "bestObjV": 3132.891575375484,
        "bestParams": [
            4433.386914713176,
            39.45525610380354,
            5.353746696228918,
            0.29658773257573146
        ]
    },
    {
        "sub_start": 1754.5,
        "sub_end": 2318.0,
        "bestObjV": 2922.6272866952704,
        "bestParams": [
            4790.739734235332,
            37.424019220829464,
            3.329139240256355,
            0.12802736940713041
        ]
    },
    {
        "sub_start": 1808.0,
        "sub_end": 2318.0,
        "bestObjV": 1107.0587054856942,
        "bestParams": [
            2646.540284710262,
            34.70262618052142,
            4.319371190074246,
            0.717006274226107
        ]
    },
    {
        "sub_start": 1861.5,
        "sub_end": 2318.0,
        "bestObjV": 661.8221295866241,
        "bestParams": [
            4483.152195180233,
            34.86113345487618,
            2.232336464961745,
            0.19372604148552183
        ]
    },
    {
        "sub_start": 1915.0,
        "sub_end": 2318.0,
        "bestObjV": 588.7254794896727,
        "bestParams": [
            2576.767859850283,
            1.3290206757549599,
            0.0,
            0.6317944795561207
        ]
    },
    {
        "sub_start": 1968.5,
        "sub_end": 2318.0,
        "bestObjV": 417.5017894553288,
        "bestParams": [
            4838.0,
            12.32291743542363,
            6.283185307179586,
            0.5242426478094991
        ]
    },
    {
        "sub_start": 2022.0,
        "sub_end": 2318.0,
        "bestObjV": 353.7433752806809,
        "bestParams": [
            3486.871272912561,
            36.21575058298002,
            3.1525989816847124,
            0.8076679653621076
        ]
    }
]