[
    {
        "sub_start": 0.0,
        "sub_end": 164.0,
        "bestObjV": 8783226.525745386,
        "bestParams": [
            166.73045714211295,
            1.4302378367470592,
            4.260508340625501,
            0.14689550793295672
        ]
    },
    {
        "sub_start": 41.0,
        "sub_end": 164.0,
        "bestObjV": 8255301.05381198,
        "bestParams": [
            198.8105946527059,
            1.385096770825327,
            4.532025120491683,
            0.14869604344751003
        ]
    },
    {
        "sub_start": 82.0,
        "sub_end": 164.0,
        "bestObjV": 8045382.78709917,
        "bestParams": [
            279.5041354571443,
            2.1284231371713735,
            0.0014252094879482014,
            0.11504694932687949
        ]
    },
    {
        "sub_start": 0.0,
        "sub_end": 163.0,
        "bestObjV": 7708700.874088964,
        "bestParams": [
            167.0023759089999,
            0.9306487163921995,
            3.2335377161616594,
            0.22013470971525673
        ]
    },
    {
        "sub_start": 41.0,
        "sub_end": 163.0,
        "bestObjV": 7401137.8090306325,
        "bestParams": [
            178.4681710953807,
            1.2873200961168818,
            5.234678076530249,
            0.2211965511853971
        ]
    },
    {
        "sub_start": 82.0,
        "sub_end": 163.0,
        "bestObjV": 6821929.254205251,
        "bestParams": [
            163.75493149050618,
            0.3227330645340043,
            5.94538663434328,
            0.6126679135208256
        ]
    },
    {
        "sub_start": 0.0,
        "sub_end": 162.0,
        "bestObjV": 7161419.448409942,
        "bestParams": [
            170.0658643558197,
            1.3897376584876886,
            4.397513917321461,
            0.15786748999942368
        ]
    },
    {
        "sub_start": 41.0,
        "sub_end": 162.0,
        "bestObjV": 6570019.273026219,
        "bestParams": [
            184.27216533970346,
            2.3794987136464085,
            3.3379230055310125,
            0.1043690214539895
        ]
    },
    {
        "sub_start": 82.0,
        "sub_end": 162.0,
        "bestObjV": 5541786.023285589,
        "bestParams": [
            163.2602252511854,
            3.6247221660334894,
            0.06849250065565092,
            0.10496831697818686
        ]
    },
    {
        "sub_start": 0.0,
        "sub_end": 161.0,
        "bestObjV": 7168521.662513607,
        "bestParams": [
            177.9542520307438,
            1.007141501222053,
            6.1325102566807095,
            0.1267909735627261
        ]
    },
    {
        "sub_start": 41.0,
        "sub_end": 161.0,
        "bestObjV": 6492014.090010511,
        "bestParams": [
            208.23712500863545,
            1.6556213567667744,
            6.238701325277911,
            0.1178875651375516
        ]
    },
    {
        "sub_start": 82.0,
        "sub_end": 161.0,
        "bestObjV": 6164818.440579546,
        "bestParams": [
            664.225297861581,
            5.769096534411191,
            5.96808998498637,
            0.5070743971018964
        ]
    },
    {
        "sub_start": 0.0,
        "sub_end": 160.0,
        "bestObjV": 7001431.886237086,
        "bestParams": [
            184.5891872581901,
            1.1056712046745387,
            2.511565489352038,
            0.10394442557575677
        ]
    },
    {
        "sub_start": 41.0,
        "sub_end": 160.0,
        "bestObjV": 6147558.875891196,
        "bestParams": [
            194.69579749369333,
            2.563147545898401,
            2.194077549082332,
            0.14237920632122558
        ]
    },
    {
        "sub_start": 82.0,
        "sub_end": 160.0,
        "bestObjV": 5736120.190958345,
        "bestParams": [
            412.4640722482922,
            13.171979022659851,
            1.4711214598617923,
            0.10274960046009651
        ]
    },
    {
        "sub_start": 0.0,
        "sub_end": 159.0,
        "bestObjV": 6843559.679963622,
        "bestParams": [
            159.33461850514894,
            0.942103075900067,
            2.46324741973199,
            0.13591679913743562
        ]
    },
    {
        "sub_start": 41.0,
        "sub_end": 159.0,
        "bestObjV": 5630299.304417143,
        "bestParams": [
            185.1737459924649,
            2.798727122442526,
            1.512918853404531,
            0.3874641010660381
        ]
    },
    {
        "sub_start": 82.0,
        "sub_end": 159.0,
        "bestObjV": 4542753.057730092,
        "bestParams": [
            160.45585578245124,
            2.22746038277553,
            1.7854123395640749,
            0.21562275636396244
        ]
    }
]