[
    {
        "sub_start": 16858.0,
        "sub_end": 18121.0,
        "bestObjV": 1806444.209303094,
        "bestParams": [
            18245.70631199112,
            8.997231100080645,
            0.9
        ]
    },
    {
        "sub_start": 16921.15,
        "sub_end": 18121.0,
        "bestObjV": 1797368.0580869874,
        "bestParams": [
            18262.882637340146,
            9.620858895071354,
            0.9
        ]
    },
    {
        "sub_start": 16984.300000000003,
        "sub_end": 18121.0,
        "bestObjV": 2170229.561888435,
        "bestParams": [
            20641.0,
            0.11542979708476997,
            0.9
        ]
    },
    {
        "sub_start": 17047.450000000004,
        "sub_end": 18121.0,
        "bestObjV": 1799459.71849596,
        "bestParams": [
            18678.464919028484,
            15.991205716620414,
            0.9
        ]
    },
    {
        "sub_start": 17110.600000000006,
        "sub_end": 18121.0,
        "bestObjV": 1767568.4657694004,
        "bestParams": [
            18239.26618542815,
            8.991173856704027,
            0.9
        ]
    },
    {
        "sub_start": 17173.750000000007,
        "sub_end": 18121.0,
        "bestObjV": 2042422.2007954016,
        "bestParams": [
            18195.31781750573,
            0.07944724357404549,
            0.30839366711579397
        ]
    },
    {
        "sub_start": 17236.90000000001,
        "sub_end": 18121.0,
        "bestObjV": 1730475.2482210943,
        "bestParams": [
            18915.019250222947,
            20.811742620735338,
            0.9
        ]
    },
    {
        "sub_start": 17300.05000000001,
        "sub_end": 18121.0,
        "bestObjV": 1653382.193716111,
        "bestParams": [
            19334.99058778216,
            29.80745689346327,
            0.6949968053084299
        ]
    },
    {
        "sub_start": 17363.20000000001,
        "sub_end": 18121.0,
        "bestObjV": 1618241.427482863,
        "bestParams": [
            19794.625913942953,
            40.0,
            0.3998686416215705
        ]
    },
    {
        "sub_start": 17426.350000000013,
        "sub_end": 18121.0,
        "bestObjV": 1327883.4229276055,
        "bestParams": [
            19248.837518390937,
            40.0,
            0.9
        ]
    },
    {
        "sub_start": 17489.500000000015,
        "sub_end": 18121.0,
        "bestObjV": 1261370.3707667887,
        "bestParams": [
            19221.2606078997,
            40.0,
            0.9
        ]
    },
    {
        "sub_start": 17552.650000000016,
        "sub_end": 18121.0,
        "bestObjV": 1100829.4230909476,
        "bestParams": [
            19505.817339416637,
            40.0,
            0.9
        ]
    },
    {
        "sub_start": 17615.800000000017,
        "sub_end": 18121.0,
        "bestObjV": 970194.0025477858,
        "bestParams": [
            19641.5568434335,
            40.0,
            0.9
        ]
    },
    {
        "sub_start": 17678.95000000002,
        "sub_end": 18121.0,
        "bestObjV": 950630.1757903224,
        "bestParams": [
            19642.86868988948,
            40.0,
            0.9
        ]
    },
    {
        "sub_start": 17742.10000000002,
        "sub_end": 18121.0,
        "bestObjV": 541895.0221639164,
        "bestParams": [
            20641.0,
            17.94618691265053,
            0.9
        ]
    },
    {
        "sub_start": 16858.0,
        "sub_end": 18116.0,
        "bestObjV": 1779845.7681818232,
        "bestParams": [
            18283.88557048757,
            9.861662400864033,
            0.9
        ]
    },
    {
        "sub_start": 16921.15,
        "sub_end": 18116.0,
        "bestObjV": 1772049.1776842168,
        "bestParams": [
            18245.512945175153,
            9.25502573348048,
            0.8991248602299634
        ]
    },
    {
        "sub_start": 16984.300000000003,
        "sub_end": 18116.0,
        "bestObjV": 2164136.348575433,
        "bestParams": [
            20636.0,
            0.13078282475235353,
            0.9
        ]
    },
    {
        "sub_start": 17047.450000000004,
        "sub_end": 18116.0,
        "bestObjV": 1757372.237257234,
        "bestParams": [
            18233.183782965447,
            8.920617931170144,
            0.9
        ]
    },
    {
        "sub_start": 17110.600000000006,
        "sub_end": 18116.0,
        "bestObjV": 2127667.9399267985,
        "bestParams": [
            20636.0,
            0.10978131717086026,
            0.9
        ]
    },
    {
        "sub_start": 17173.750000000007,
        "sub_end": 18116.0,
        "bestObjV": 1738873.0030540163,
        "bestParams": [
            18269.91748604321,
            9.60032547489949,
            0.9
        ]
    },
    {
        "sub_start": 17236.90000000001,
        "sub_end": 18116.0,
        "bestObjV": 1702171.8718661699,
        "bestParams": [
            18740.42083897567,
            17.972372624576522,
            0.9
        ]
    },
    {
        "sub_start": 17300.05000000001,
        "sub_end": 18116.0,
        "bestObjV": 1550497.4330784837,
        "bestParams": [
            18545.580658095336,
            31.232080556297966,
            0.9
        ]
    },
    {
        "sub_start": 17363.20000000001,
        "sub_end": 18116.0,
        "bestObjV": 1584949.265868154,
        "bestParams": [
            19554.961990016433,
            35.828437940902816,
            0.3303155864842787
        ]
    },
    {
        "sub_start": 17426.350000000013,
        "sub_end": 18116.0,
        "bestObjV": 1300102.2190472984,
        "bestParams": [
            19277.343520675127,
            40.0,
            0.9
        ]
    },
    {
        "sub_start": 17489.500000000015,
        "sub_end": 18116.0,
        "bestObjV": 1236572.1501114496,
        "bestParams": [
            19492.79022227447,
            40.0,
            0.6474106071835602
        ]
    },
    {
        "sub_start": 17552.650000000016,
        "sub_end": 18116.0,
        "bestObjV": 1032063.6337988086,
        "bestParams": [
            19491.961711833712,
            40.0,
            0.9
        ]
    },
    {
        "sub_start": 17615.800000000017,
        "sub_end": 18116.0,
        "bestObjV": 919020.8353406902,
        "bestParams": [
            19599.501445230653,
            40.0,
            0.9
        ]
    },
    {
        "sub_start": 17678.95000000002,
        "sub_end": 18116.0,
        "bestObjV": 899908.687342101,
        "bestParams": [
            19599.2240850198,
            40.0,
            0.9
        ]
    },
    {
        "sub_start": 17742.10000000002,
        "sub_end": 18116.0,
        "bestObjV": 523381.2970194864,
        "bestParams": [
            20636.0,
            28.228932414939596,
            0.9
        ]
    },
    {
        "sub_start": 16858.0,
        "sub_end": 18111.0,
        "bestObjV": 1718509.8611365005,
        "bestParams": [
            18259.329123676274,
            9.321146043604575,
            0.9
        ]
    },
    {
        "sub_start": 16921.15,
        "sub_end": 18111.0,
        "bestObjV": 1714251.4776531106,
        "bestParams": [
            18365.006566732787,
            11.029781161698578,
            0.9
        ]
    },
    {
        "sub_start": 16984.300000000003,
        "sub_end": 18111.0,
        "bestObjV": 1702180.763708622,
        "bestParams": [
            18443.381856794593,
            12.49279896562639,
            0.9
        ]
    },
    {
        "sub_start": 17047.450000000004,
        "sub_end": 18111.0,
        "bestObjV": 2137770.1616263413,
        "bestParams": [
            20631.0,
            0.13966847796414014,
            0.9
        ]
    },
    {
        "sub_start": 17110.600000000006,
        "sub_end": 18111.0,
        "bestObjV": 1688360.6503697475,
        "bestParams": [
            18389.27690713809,
            11.618978169860705,
            0.9
        ]
    },
    {
        "sub_start": 17173.750000000007,
        "sub_end": 18111.0,
        "bestObjV": 1682210.9611437405,
        "bestParams": [
            18422.585308188514,
            12.103377068428111,
            0.9
        ]
    },
    {
        "sub_start": 17236.90000000001,
        "sub_end": 18111.0,
        "bestObjV": 1633985.3957432648,
        "bestParams": [
            18555.267755446628,
            14.815821188129918,
            0.8616013704476517
        ]
    },
    {
        "sub_start": 17300.05000000001,
        "sub_end": 18111.0,
        "bestObjV": 1513629.1810971368,
        "bestParams": [
            18564.206416574078,
            31.942705234895314,
            0.9
        ]
    },
    {
        "sub_start": 17363.20000000001,
        "sub_end": 18111.0,
        "bestObjV": 1961643.8401594784,
        "bestParams": [
            20631.0,
            0.21664891723908072,
            0.9
        ]
    },
    {
        "sub_start": 17426.350000000013,
        "sub_end": 18111.0,
        "bestObjV": 1214553.3504061815,
        "bestParams": [
            19373.114290371457,
            40.0,
            0.3057813332985953
        ]
    },
    {
        "sub_start": 17489.500000000015,
        "sub_end": 18111.0,
        "bestObjV": 1133762.1605845017,
        "bestParams": [
            19483.4944949006,
            40.0,
            0.27864963603784465
        ]
    },
    {
        "sub_start": 17552.650000000016,
        "sub_end": 18111.0,
        "bestObjV": 914817.980246916,
        "bestParams": [
            19473.943022976466,
            40.0,
            0.9
        ]
    },
    {
        "sub_start": 17615.800000000017,
        "sub_end": 18111.0,
        "bestObjV": 820384.4621894597,
        "bestParams": [
            19550.934807394922,
            40.0,
            0.9
        ]
    },
    {
        "sub_start": 17678.95000000002,
        "sub_end": 18111.0,
        "bestObjV": 801975.5822608331,
        "bestParams": [
            19554.499509297995,
            40.0,
            0.8988214078558612
        ]
    },
    {
        "sub_start": 17742.10000000002,
        "sub_end": 18111.0,
        "bestObjV": 463480.11908559676,
        "bestParams": [
            20631.0,
            38.48759445662779,
            0.9
        ]
    },
    {
        "sub_start": 16858.0,
        "sub_end": 18106.0,
        "bestObjV": 1687340.7284013596,
        "bestParams": [
            18322.94239312015,
            10.210609854299367,
            0.8596079585850321
        ]
    },
    {
        "sub_start": 16921.15,
        "sub_end": 18106.0,
        "bestObjV": 1674638.9649544326,
        "bestParams": [
            18391.662963568153,
            11.482956334544605,
            0.8474338848876941
        ]
    },
    {
        "sub_start": 16984.300000000003,
        "sub_end": 18106.0,
        "bestObjV": 2130029.12764502,
        "bestParams": [
            20626.0,
            0.10632123964740757,
            0.9
        ]
    },
    {
        "sub_start": 17047.450000000004,
        "sub_end": 18106.0,
        "bestObjV": 1660750.8464052044,
        "bestParams": [
            18467.24082842806,
            12.852736247171938,
            0.8494035068014822
        ]
    },
    {
        "sub_start": 17110.600000000006,
        "sub_end": 18106.0,
        "bestObjV": 1649629.5474311153,
        "bestParams": [
            18452.72429527653,
            12.62883686520707,
            0.8569830933994296
        ]
    },
    {
        "sub_start": 17173.750000000007,
        "sub_end": 18106.0,
        "bestObjV": 1644709.8952463763,
        "bestParams": [
            18425.581812743312,
            12.071735440954953,
            0.8802623006933226
        ]
    },
    {
        "sub_start": 17236.90000000001,
        "sub_end": 18106.0,
        "bestObjV": 1592497.6326705285,
        "bestParams": [
            18533.390296043613,
            14.432815358646753,
            0.7919054873336426
        ]
    },
    {
        "sub_start": 17300.05000000001,
        "sub_end": 18106.0,
        "bestObjV": 1502822.8933439797,
        "bestParams": [
            18748.92954772019,
            19.432596521571558,
            0.573684683881088
        ]
    },
    {
        "sub_start": 17363.20000000001,
        "sub_end": 18106.0,
        "bestObjV": 1457162.780015847,
        "bestParams": [
            19049.10918898717,
            26.53006224241587,
            0.2713033561039349
        ]
    },
    {
        "sub_start": 17426.350000000013,
        "sub_end": 18106.0,
        "bestObjV": 1145375.765362871,
        "bestParams": [
            19395.2252485754,
            40.0,
            0.1
        ]
    },
    {
        "sub_start": 17489.500000000015,
        "sub_end": 18106.0,
        "bestObjV": 1064297.6336789906,
        "bestParams": [
            19465.797468843095,
            40.0,
            0.1
        ]
    },
    {
        "sub_start": 17552.650000000016,
        "sub_end": 18106.0,
        "bestObjV": 841506.2559218386,
        "bestParams": [
            19463.09105934906,
            40.0,
            0.9
        ]
    },
    {
        "sub_start": 17615.800000000017,
        "sub_end": 18106.0,
        "bestObjV": 758373.398446193,
        "bestParams": [
            19520.735054505425,
            40.0,
            0.9
        ]
    },
    {
        "sub_start": 17678.95000000002,
        "sub_end": 18106.0,
        "bestObjV": 740479.9227429801,
        "bestParams": [
            19524.381891534973,
            40.0,
            0.9
        ]
    },
    {
        "sub_start": 17742.10000000002,
        "sub_end": 18106.0,
        "bestObjV": 423114.2469360101,
        "bestParams": [
            20424.74375032732,
            40.0,
            0.9
        ]
    },
    {
        "sub_start": 16858.0,
        "sub_end": 18101.0,
        "bestObjV": 2167732.7642740067,
        "bestParams": [
            20621.0,
            12.619489046835453,
            0.1
        ]
    },
    {
        "sub_start": 16921.15,
        "sub_end": 18101.0,
        "bestObjV": 2137066.5004051845,
        "bestParams": [
            20621.0,
            0.11805710606395786,
            0.9
        ]
    },
    {
        "sub_start": 16984.300000000003,
        "sub_end": 18101.0,
        "bestObjV": 2128281.304428894,
        "bestParams": [
            20621.0,
            0.08384658666776884,
            0.9
        ]
    },
    {
        "sub_start": 17047.450000000004,
        "sub_end": 18101.0,
        "bestObjV": 2126875.133198787,
        "bestParams": [
            20621.0,
            0.11244939381581605,
            0.9
        ]
    },
    {
        "sub_start": 17110.600000000006,
        "sub_end": 18101.0,
        "bestObjV": 1636187.301605268,
        "bestParams": [
            18441.809726924464,
            12.461474876472296,
            0.8058055966944222
        ]
    },
    {
        "sub_start": 17173.750000000007,
        "sub_end": 18101.0,
        "bestObjV": 1628980.7701720246,
        "bestParams": [
            18437.966135857903,
            12.37981196280291,
            0.8294739282949801
        ]
    },
    {
        "sub_start": 17236.90000000001,
        "sub_end": 18101.0,
        "bestObjV": 1576991.3039539524,
        "bestParams": [
            18471.338018650964,
            13.54016301531298,
            0.7800299826964517
        ]
    },
    {
        "sub_start": 17300.05000000001,
        "sub_end": 18101.0,
        "bestObjV": 1950959.1500762631,
        "bestParams": [
            20621.0,
            0.1450300839704372,
            0.9
        ]
    },
    {
        "sub_start": 17363.20000000001,
        "sub_end": 18101.0,
        "bestObjV": 1433281.2458789314,
        "bestParams": [
            18942.464039966962,
            24.465320313418353,
            0.2510813950739908
        ]
    },
    {
        "sub_start": 17426.350000000013,
        "sub_end": 18101.0,
        "bestObjV": 1111559.1915645632,
        "bestParams": [
            19383.236761727167,
            40.0,
            0.1
        ]
    },
    {
        "sub_start": 17489.500000000015,
        "sub_end": 18101.0,
        "bestObjV": 1030003.2122496538,
        "bestParams": [
            19449.634749743676,
            40.0,
            0.1
        ]
    },
    {
        "sub_start": 17552.650000000016,
        "sub_end": 18101.0,
        "bestObjV": 805303.2293802324,
        "bestParams": [
            19453.782899944432,
            40.0,
            0.9
        ]
    },
    {
        "sub_start": 17615.800000000017,
        "sub_end": 18101.0,
        "bestObjV": 728792.18732774,
        "bestParams": [
            19505.33240615311,
            40.0,
            0.9
        ]
    },
    {
        "sub_start": 17678.95000000002,
        "sub_end": 18101.0,
        "bestObjV": 711369.630383527,
        "bestParams": [
            19505.203339657164,
            40.0,
            0.9
        ]
    },
    {
        "sub_start": 17742.10000000002,
        "sub_end": 18101.0,
        "bestObjV": 405070.8076455747,
        "bestParams": [
            20279.1769351951,
            40.0,
            0.9
        ]
    },
    {
        "sub_start": 16858.0,
        "sub_end": 18096.0,
        "bestObjV": 1656681.5466749785,
        "bestParams": [
            18361.350711463077,
            10.967469870673906,
            0.8334275082673331
        ]
    },
    {
        "sub_start": 16921.15,
        "sub_end": 18096.0,
        "bestObjV": 2136207.8343196097,
        "bestParams": [
            20616.0,
            0.10654606311935755,
            0.9
        ]
    },
    {
        "sub_start": 16984.300000000003,
        "sub_end": 18096.0,
        "bestObjV": 2127580.56451979,
        "bestParams": [
            20616.0,
            0.0919287372105191,
            0.9
        ]
    },
    {
        "sub_start": 17047.450000000004,
        "sub_end": 18096.0,
        "bestObjV": 2126184.0858553136,
        "bestParams": [
            20616.0,
            0.0952809040807654,
            0.9
        ]
    },
    {
        "sub_start": 17110.600000000006,
        "sub_end": 18096.0,
        "bestObjV": 1620935.4759170578,
        "bestParams": [
            18363.746644224193,
            11.025838366575401,
            0.7852739929771675
        ]
    },
    {
        "sub_start": 17173.750000000007,
        "sub_end": 18096.0,
        "bestObjV": 1613599.0351645865,
        "bestParams": [
            18379.48654490836,
            11.292820081791037,
            0.8066156402371171
        ]
    },
    {
        "sub_start": 17236.90000000001,
        "sub_end": 18096.0,
        "bestObjV": 1558718.9501181846,
        "bestParams": [
            18491.029221038232,
            13.72330281767002,
            0.7023420521142953
        ]
    },
    {
        "sub_start": 17300.05000000001,
        "sub_end": 18096.0,
        "bestObjV": 1947496.5237030874,
        "bestParams": [
            20616.0,
            0.1846628816493407,
            0.9
        ]
    },
    {
        "sub_start": 17363.20000000001,
        "sub_end": 18096.0,
        "bestObjV": 1408969.3842414252,
        "bestParams": [
            18896.84977417339,
            23.54334726461951,
            0.1843051613560397
        ]
    },
    {
        "sub_start": 17426.350000000013,
        "sub_end": 18096.0,
        "bestObjV": 1079688.0935738764,
        "bestParams": [
            19374.118860183597,
            40.0,
            0.1
        ]
    },
    {
        "sub_start": 17489.500000000015,
        "sub_end": 18096.0,
        "bestObjV": 998110.6315640127,
        "bestParams": [
            19434.09149743846,
            40.0,
            0.1
        ]
    },
    {
        "sub_start": 17552.650000000016,
        "sub_end": 18096.0,
        "bestObjV": 771412.4969775598,
        "bestParams": [
            19444.366418482587,
            40.0,
            0.9
        ]
    },
    {
        "sub_start": 17615.800000000017,
        "sub_end": 18096.0,
        "bestObjV": 700758.0817560845,
        "bestParams": [
            19484.81557277454,
            40.0,
            0.9
        ]
    },
    {
        "sub_start": 17678.95000000002,
        "sub_end": 18096.0,
        "bestObjV": 683878.5896511571,
        "bestParams": [
            19487.10190835582,
            40.0,
            0.9
        ]
    },
    {
        "sub_start": 17742.10000000002,
        "sub_end": 18096.0,
        "bestObjV": 357584.7299457009,
        "bestParams": [
            18123.980270849228,
            3.9816810823785125,
            0.7993073391733158
        ]
    }
]